ai/backend/krunner/alpine/__init__.py
ai/backend/krunner/alpine/krunner-env.musllinux_1_2.x86_64.tar.xz
ai/backend/krunner/alpine/krunner-python.musllinux_1_2.txt
ai/backend/krunner/alpine/krunner-version.musllinux_1_2.txt
ai/backend/krunner/alpine/plugin.py
ai/backend/krunner/alpine/ttyd_linux.x86_64.bin
ai/backend/krunner/alpine/versions.txt
ai/backend/krunner/alpine/licenses/LICENSE.async-timeout.txt
ai/backend/krunner/alpine/licenses/LICENSE.attrs.txt
ai/backend/krunner/alpine/licenses/LICENSE.ipython-genutils.md
ai/backend/krunner/alpine/licenses/LICENSE.janus.txt
ai/backend/krunner/alpine/licenses/LICENSE.jupyter-client.md
ai/backend/krunner/alpine/licenses/LICENSE.jupyter-core.md
ai/backend/krunner/alpine/licenses/LICENSE.msgpack.txt
ai/backend/krunner/alpine/licenses/LICENSE.python-dateutil.txt
ai/backend/krunner/alpine/licenses/LICENSE.pyzmq.txt
ai/backend/krunner/alpine/licenses/LICENSE.six.txt
ai/backend/krunner/alpine/licenses/LICENSE.tornado.txt
ai/backend/krunner/alpine/licenses/LICENSE.traitlets.md
ai/backend/krunner/alpine/licenses/LICENSE.uvloop.txt
backend_ai_krunner_alpine-5.4.0.dist-info/licenses/LICENSE
backend_ai_krunner_alpine-5.4.0.dist-info/licenses/src/ai/backend/krunner/alpine/licenses/LICENSE.async-timeout.txt
backend_ai_krunner_alpine-5.4.0.dist-info/licenses/src/ai/backend/krunner/alpine/licenses/LICENSE.attrs.txt
backend_ai_krunner_alpine-5.4.0.dist-info/licenses/src/ai/backend/krunner/alpine/licenses/LICENSE.ipython-genutils.md
backend_ai_krunner_alpine-5.4.0.dist-info/licenses/src/ai/backend/krunner/alpine/licenses/LICENSE.janus.txt
backend_ai_krunner_alpine-5.4.0.dist-info/licenses/src/ai/backend/krunner/alpine/licenses/LICENSE.jupyter-client.md
backend_ai_krunner_alpine-5.4.0.dist-info/licenses/src/ai/backend/krunner/alpine/licenses/LICENSE.jupyter-core.md
backend_ai_krunner_alpine-5.4.0.dist-info/licenses/src/ai/backend/krunner/alpine/licenses/LICENSE.msgpack.txt
backend_ai_krunner_alpine-5.4.0.dist-info/licenses/src/ai/backend/krunner/alpine/licenses/LICENSE.python-dateutil.txt
backend_ai_krunner_alpine-5.4.0.dist-info/licenses/src/ai/backend/krunner/alpine/licenses/LICENSE.pyzmq.txt
backend_ai_krunner_alpine-5.4.0.dist-info/licenses/src/ai/backend/krunner/alpine/licenses/LICENSE.six.txt
backend_ai_krunner_alpine-5.4.0.dist-info/licenses/src/ai/backend/krunner/alpine/licenses/LICENSE.tornado.txt
backend_ai_krunner_alpine-5.4.0.dist-info/licenses/src/ai/backend/krunner/alpine/licenses/LICENSE.traitlets.md
backend_ai_krunner_alpine-5.4.0.dist-info/licenses/src/ai/backend/krunner/alpine/licenses/LICENSE.uvloop.txt
backend_ai_krunner_alpine-5.4.0.dist-info/METADATA
backend_ai_krunner_alpine-5.4.0.dist-info/WHEEL
backend_ai_krunner_alpine-5.4.0.dist-info/entry_points.txt
backend_ai_krunner_alpine-5.4.0.dist-info/top_level.txt
backend_ai_krunner_alpine-5.4.0.dist-info/RECORD
